soset/__init__.py
soset/constructor.py
soset/models.py
soset-0.1.1.dist-info/LICENSE
soset-0.1.1.dist-info/WHEEL
soset-0.1.1.dist-info/METADATA
soset-0.1.1.dist-info/RECORD
